pytest_hot_reloading/__init__.py
pytest_hot_reloading/client.py
pytest_hot_reloading/daemon.py
pytest_hot_reloading/jurigged_daemon_signalers.py
pytest_hot_reloading/plugin.py
pytest_hot_reloading/py.typed
pytest_hot_reloading/workarounds.py
pytest_hot_reloading-0.1.0a19.dist-info/LICENSE
pytest_hot_reloading-0.1.0a19.dist-info/METADATA
pytest_hot_reloading-0.1.0a19.dist-info/WHEEL
pytest_hot_reloading-0.1.0a19.dist-info/RECORD
