Metadata-Version: 2.1
Name: pytest-hot-reloading
Version: 0.1.0a19
Summary: 
Author: James Hutchison
Author-email: jamesghutchison@proton.me
Requires-Python: >=3.10,<4.0
Classifier: Programming Language :: Python :: 3
Classifier: Programming Language :: Python :: 3.10
Classifier: Programming Language :: Python :: 3.11
Classifier: Programming Language :: Python :: 3.12
Requires-Dist: cachetools (>=5.3.0,<6.0.0)
Requires-Dist: jurigged (>=0.5.5,<0.6.0)
